ChitChatPY/__init__.py
ChitChatPY/main.py
ChitChatPY-0.0.2.dist-info/METADATA
ChitChatPY-0.0.2.dist-info/WHEEL
ChitChatPY-0.0.2.dist-info/top_level.txt
ChitChatPY-0.0.2.dist-info/zip-safe
ChitChatPY-0.0.2.dist-info/RECORD
